{"title":"Women NGram-1","total":"27240","sex":"Women","data":[{"ngram":"looking","groupBy":"","groupByValue":"","count":"1646"},{"ngram":"fun","groupBy":"","groupByValue":"","count":"980"},{"ngram":"lets","groupBy":"","groupByValue":"","count":"337"},{"ngram":"hi","groupBy":"","groupByValue":"","count":"303"},{"ngram":"love","groupBy":"","groupByValue":"","count":"290"},{"ngram":"life","groupBy":"","groupByValue":"","count":"251"},{"ngram":"just","groupBy":"","groupByValue":"","count":"245"},{"ngram":"good","groupBy":"","groupByValue":"","count":"239"},{"ngram":"male","groupBy":"","groupByValue":"","count":"239"},{"ngram":"hello","groupBy":"","groupByValue":"","count":"237"},{"ngram":"want","groupBy":"","groupByValue":"","count":"218"},{"ngram":"im","groupBy":"","groupByValue":"","count":"212"},{"ngram":"guy","groupBy":"","groupByValue":"","count":"210"},{"ngram":"ladies","groupBy":"","groupByValue":"","count":"208"},{"ngram":"time","groupBy":"","groupByValue":"","count":"186"},{"ngram":"discreet","groupBy":"","groupByValue":"","count":"180"},{"ngram":"seeking","groupBy":"","groupByValue":"","count":"171"},{"ngram":"man","groupBy":"","groupByValue":"","count":"166"},{"ngram":"can","groupBy":"","groupByValue":"","count":"166"},{"ngram":"like","groupBy":"","groupByValue":"","count":"165"},{"ngram":"hot","groupBy":"","groupByValue":"","count":"164"},{"ngram":"please","groupBy":"","groupByValue":"","count":"160"},{"ngram":"meet","groupBy":"","groupByValue":"","count":"150"},{"ngram":"woman","groupBy":"","groupByValue":"","count":"149"},{"ngram":"ready","groupBy":"","groupByValue":"","count":"137"},{"ngram":"need","groupBy":"","groupByValue":"","count":"135"},{"ngram":"women","groupBy":"","groupByValue":"","count":"133"},{"ngram":"get","groupBy":"","groupByValue":"","count":"125"},{"ngram":"one","groupBy":"","groupByValue":"","count":"116"},{"ngram":"let","groupBy":"","groupByValue":"","count":"116"},{"ngram":"sexy","groupBy":"","groupByValue":"","count":"112"},{"ngram":"new","groupBy":"","groupByValue":"","count":"108"},{"ngram":"attached","groupBy":"","groupByValue":"","count":"108"},{"ngram":"someone","groupBy":"","groupByValue":"","count":"107"},{"ngram":"lady","groupBy":"","groupByValue":"","count":"107"},{"ngram":"married","groupBy":"","groupByValue":"","count":"107"},{"ngram":"play","groupBy":"","groupByValue":"","count":"103"},{"ngram":"excitement","groupBy":"","groupByValue":"","count":"102"},{"ngram":"hey","groupBy":"","groupByValue":"","count":"102"},{"ngram":"passion","groupBy":"","groupByValue":"","count":"101"},{"ngram":"nice","groupBy":"","groupByValue":"","count":"100"},{"ngram":"something","groupBy":"","groupByValue":"","count":"97"},{"ngram":"young","groupBy":"","groupByValue":"","count":"96"},{"ngram":"adventure","groupBy":"","groupByValue":"","count":"96"},{"ngram":"pleasure","groupBy":"","groupByValue":"","count":"95"},{"ngram":"u","groupBy":"","groupByValue":"","count":"94"},{"ngram":"times","groupBy":"","groupByValue":"","count":"94"},{"ngram":"sex","groupBy":"","groupByValue":"","count":"93"},{"ngram":"come","groupBy":"","groupByValue":"","count":"90"},{"ngram":"attractive","groupBy":"","groupByValue":"","count":"90"},{"ngram":"will","groupBy":"","groupByValue":"","count":"89"},{"ngram":"seeks","groupBy":"","groupByValue":"","count":"82"},{"ngram":"great","groupBy":"","groupByValue":"","count":"81"},{"ngram":"try","groupBy":"","groupByValue":"","count":"80"},{"ngram":"open","groupBy":"","groupByValue":"","count":"79"},{"ngram":"little","groupBy":"","groupByValue":"","count":"79"},{"ngram":"tall","groupBy":"","groupByValue":"","count":"79"},{"ngram":"make","groupBy":"","groupByValue":"","count":"76"},{"ngram":"handsome","groupBy":"","groupByValue":"","count":"71"},{"ngram":"take","groupBy":"","groupByValue":"","count":"67"},{"ngram":"know","groupBy":"","groupByValue":"","count":"67"},{"ngram":"always","groupBy":"","groupByValue":"","count":"66"},{"ngram":"lover","groupBy":"","groupByValue":"","count":"63"},{"ngram":"romantic","groupBy":"","groupByValue":"","count":"63"},{"ngram":"live","groupBy":"","groupByValue":"","count":"63"},{"ngram":"anything","groupBy":"","groupByValue":"","count":"62"},{"ngram":"spice","groupBy":"","groupByValue":"","count":"60"},{"ngram":"short","groupBy":"","groupByValue":"","count":"60"},{"ngram":"wild","groupBy":"","groupByValue":"","count":"60"},{"ngram":"sensual","groupBy":"","groupByValue":"","count":"60"},{"ngram":"enjoy","groupBy":"","groupByValue":"","count":"59"},{"ngram":"see","groupBy":"","groupByValue":"","count":"59"},{"ngram":"lookin","groupBy":"","groupByValue":"","count":"59"},{"ngram":"female","groupBy":"","groupByValue":"","count":"59"},{"ngram":"special","groupBy":"","groupByValue":"","count":"59"},{"ngram":"real","groupBy":"","groupByValue":"","count":"58"},{"ngram":"wanna","groupBy":"","groupByValue":"","count":"58"},{"ngram":"professional","groupBy":"","groupByValue":"","count":"57"},{"ngram":"give","groupBy":"","groupByValue":"","count":"57"},{"ngram":"right","groupBy":"","groupByValue":"","count":"56"},{"ngram":"go","groupBy":"","groupByValue":"","count":"56"},{"ngram":"well","groupBy":"","groupByValue":"","count":"56"},{"ngram":"look","groupBy":"","groupByValue":"","count":"56"},{"ngram":"passionate","groupBy":"","groupByValue":"","count":"56"},{"ngram":"minded","groupBy":"","groupByValue":"","count":"54"},{"ngram":"erotic","groupBy":"","groupByValue":"","count":"54"},{"ngram":"together","groupBy":"","groupByValue":"","count":"54"},{"ngram":"fit","groupBy":"","groupByValue":"","count":"53"},{"ngram":"loving","groupBy":"","groupByValue":"","count":"53"},{"ngram":"dont","groupBy":"","groupByValue":"","count":"52"},{"ngram":"exciting","groupBy":"","groupByValue":"","count":"52"},{"ngram":"willing","groupBy":"","groupByValue":"","count":"51"},{"ngram":"dark","groupBy":"","groupByValue":"","count":"51"},{"ngram":"waiting","groupBy":"","groupByValue":"","count":"51"},{"ngram":"creative","groupBy":"","groupByValue":"","count":"50"},{"ngram":"single","groupBy":"","groupByValue":"","count":"50"},{"ngram":"sweet","groupBy":"","groupByValue":"","count":"48"},{"ngram":"4","groupBy":"","groupByValue":"","count":"46"},{"ngram":"encounters","groupBy":"","groupByValue":"","count":"46"},{"ngram":"talk","groupBy":"","groupByValue":"","count":"46"},{"ngram":"wants","groupBy":"","groupByValue":"","count":"46"},{"ngram":"curious","groupBy":"","groupByValue":"","count":"46"},{"ngram":"strings","groupBy":"","groupByValue":"","count":"46"},{"ngram":"big","groupBy":"","groupByValue":"","count":"45"},{"ngram":"friend","groupBy":"","groupByValue":"","count":"45"},{"ngram":"share","groupBy":"","groupByValue":"","count":"44"},{"ngram":"world","groupBy":"","groupByValue":"","count":"43"},{"ngram":"never","groupBy":"","groupByValue":"","count":"43"},{"ngram":"relationship","groupBy":"","groupByValue":"","count":"42"},{"ngram":"beautiful","groupBy":"","groupByValue":"","count":"41"},{"ngram":"long","groupBy":"","groupByValue":"","count":"41"},{"ngram":"day","groupBy":"","groupByValue":"","count":"40"},{"ngram":"mature","groupBy":"","groupByValue":"","count":"40"},{"ngram":"whats","groupBy":"","groupByValue":"","count":"39"},{"ngram":"gentleman","groupBy":"","groupByValue":"","count":"38"},{"ngram":"discrete","groupBy":"","groupByValue":"","count":"38"},{"ngram":"romance","groupBy":"","groupByValue":"","count":"38"},{"ngram":"experience","groupBy":"","groupByValue":"","count":"37"},{"ngram":"bored","groupBy":"","groupByValue":"","count":"37"},{"ngram":"going","groupBy":"","groupByValue":"","count":"37"},{"ngram":"now","groupBy":"","groupByValue":"","count":"36"},{"ngram":"help","groupBy":"","groupByValue":"","count":"36"},{"ngram":"best","groupBy":"","groupByValue":"","count":"36"},{"ngram":"needs","groupBy":"","groupByValue":"","count":"36"},{"ngram":"interested","groupBy":"","groupByValue":"","count":"36"},{"ngram":"old","groupBy":"","groupByValue":"","count":"35"},{"ngram":"girl","groupBy":"","groupByValue":"","count":"35"},{"ngram":"athletic","groupBy":"","groupByValue":"","count":"34"},{"ngram":"hard","groupBy":"","groupByValue":"","count":"34"},{"ngram":"tongue","groupBy":"","groupByValue":"","count":"34"},{"ngram":"fantasy","groupBy":"","groupByValue":"","count":"34"},{"ngram":"oral","groupBy":"","groupByValue":"","count":"33"},{"ngram":"sexual","groupBy":"","groupByValue":"","count":"33"},{"ngram":"chat","groupBy":"","groupByValue":"","count":"33"},{"ngram":"mind","groupBy":"","groupByValue":"","count":"33"},{"ngram":"older","groupBy":"","groupByValue":"","count":"33"},{"ngram":"adventurous","groupBy":"","groupByValue":"","count":"33"},{"ngram":"smile","groupBy":"","groupByValue":"","count":"33"},{"ngram":"easy","groupBy":"","groupByValue":"","count":"33"},{"ngram":"find","groupBy":"","groupByValue":"","count":"32"},{"ngram":"interesting","groupBy":"","groupByValue":"","count":"32"},{"ngram":"back","groupBy":"","groupByValue":"","count":"32"},{"ngram":"clean","groupBy":"","groupByValue":"","count":"32"},{"ngram":"things","groupBy":"","groupByValue":"","count":"31"},{"ngram":"explore","groupBy":"","groupByValue":"","count":"31"},{"ngram":"ill","groupBy":"","groupByValue":"","count":"31"},{"ngram":"lonely","groupBy":"","groupByValue":"","count":"30"},{"ngram":"toronto","groupBy":"","groupByValue":"","count":"30"},{"ngram":"fantasies","groupBy":"","groupByValue":"","count":"30"},{"ngram":"anyone","groupBy":"","groupByValue":"","count":"30"},{"ngram":"wanted","groupBy":"","groupByValue":"","count":"30"},{"ngram":"people","groupBy":"","groupByValue":"","count":"30"},{"ngram":"better","groupBy":"","groupByValue":"","count":"30"},{"ngram":"fire","groupBy":"","groupByValue":"","count":"29"},{"ngram":"eyes","groupBy":"","groupByValue":"","count":"29"},{"ngram":"first","groupBy":"","groupByValue":"","count":"29"},{"ngram":"heart","groupBy":"","groupByValue":"","count":"29"},{"ngram":"got","groupBy":"","groupByValue":"","count":"29"},{"ngram":"shy","groupBy":"","groupByValue":"","count":"28"},{"ngram":"horny","groupBy":"","groupByValue":"","count":"28"},{"ngram":"loves","groupBy":"","groupByValue":"","count":"27"},{"ngram":"hands","groupBy":"","groupByValue":"","count":"27"},{"ngram":"free","groupBy":"","groupByValue":"","count":"27"},{"ngram":"nothing","groupBy":"","groupByValue":"","count":"27"},{"ngram":"girls","groupBy":"","groupByValue":"","count":"27"},{"ngram":"secret","groupBy":"","groupByValue":"","count":"27"},{"ngram":"boy","groupBy":"","groupByValue":"","count":"27"},{"ngram":"keep","groupBy":"","groupByValue":"","count":"27"},{"ngram":"warm","groupBy":"","groupByValue":"","count":"27"},{"ngram":"night","groupBy":"","groupByValue":"","count":"27"},{"ngram":"gentle","groupBy":"","groupByValue":"","count":"27"},{"ngram":"baby","groupBy":"","groupByValue":"","count":"26"},{"ngram":"ride","groupBy":"","groupByValue":"","count":"26"},{"ngram":"intelligent","groupBy":"","groupByValue":"","count":"26"},{"ngram":"intimate","groupBy":"","groupByValue":"","count":"25"},{"ngram":"able","groupBy":"","groupByValue":"","count":"25"},{"ngram":"casual","groupBy":"","groupByValue":"","count":"25"},{"ngram":"openminded","groupBy":"","groupByValue":"","count":"25"},{"ngram":"happy","groupBy":"","groupByValue":"","count":"24"},{"ngram":"encounter","groupBy":"","groupByValue":"","count":"24"},{"ngram":"satisfy","groupBy":"","groupByValue":"","count":"24"},{"ngram":"around","groupBy":"","groupByValue":"","count":"24"},{"ngram":"playmate","groupBy":"","groupByValue":"","count":"24"},{"ngram":"places","groupBy":"","groupByValue":"","count":"24"},{"ngram":"eat","groupBy":"","groupByValue":"","count":"24"},{"ngram":"say","groupBy":"","groupByValue":"","count":"23"},{"ngram":"worth","groupBy":"","groupByValue":"","count":"23"},{"ngram":"everything","groupBy":"","groupByValue":"","count":"23"},{"ngram":"honest","groupBy":"","groupByValue":"","count":"23"},{"ngram":"cute","groupBy":"","groupByValue":"","count":"23"},{"ngram":"feel","groupBy":"","groupByValue":"","count":"23"},{"ngram":"us","groupBy":"","groupByValue":"","count":"23"},{"ngram":"lick","groupBy":"","groupByValue":"","count":"23"},{"ngram":"wont","groupBy":"","groupByValue":"","count":"23"},{"ngram":"really","groupBy":"","groupByValue":"","count":"23"},{"ngram":"missing","groupBy":"","groupByValue":"","count":"23"},{"ngram":"doin","groupBy":"","groupByValue":"","count":"23"},{"ngram":"ever","groupBy":"","groupByValue":"","count":"23"},{"ngram":"bad","groupBy":"","groupByValue":"","count":"22"},{"ngram":"stop","groupBy":"","groupByValue":"","count":"22"},{"ngram":"females","groupBy":"","groupByValue":"","count":"22"},{"ngram":"away","groupBy":"","groupByValue":"","count":"22"},{"ngram":"satisfaction","groupBy":"","groupByValue":"","count":"22"},{"ngram":"game","groupBy":"","groupByValue":"","count":"22"},{"ngram":"tell","groupBy":"","groupByValue":"","count":"22"},{"ngram":"afternoon","groupBy":"","groupByValue":"","count":"22"},{"ngram":"search","groupBy":"","groupByValue":"","count":"22"},{"ngram":"every","groupBy":"","groupByValue":"","count":"22"},{"ngram":"affair","groupBy":"","groupByValue":"","count":"22"},{"ngram":"excitment","groupBy":"","groupByValue":"","count":"22"},{"ngram":"name","groupBy":"","groupByValue":"","count":"22"},{"ngram":"way","groupBy":"","groupByValue":"","count":"21"},{"ngram":"lifes","groupBy":"","groupByValue":"","count":"21"},{"ngram":"cum","groupBy":"","groupByValue":"","count":"21"},{"ngram":"touch","groupBy":"","groupByValue":"","count":"21"},{"ngram":"call","groupBy":"","groupByValue":"","count":"21"},{"ngram":"blue","groupBy":"","groupByValue":"","count":"21"},{"ngram":"fullest","groupBy":"","groupByValue":"","count":"21"},{"ngram":"different","groupBy":"","groupByValue":"","count":"20"},{"ngram":"cant","groupBy":"","groupByValue":"","count":"20"},{"ngram":"2","groupBy":"","groupByValue":"","count":"20"},{"ngram":"naughty","groupBy":"","groupByValue":"","count":"20"},{"ngram":"serious","groupBy":"","groupByValue":"","count":"20"},{"ngram":"friends","groupBy":"","groupByValue":"","count":"20"},{"ngram":"partner","groupBy":"","groupByValue":"","count":"19"},{"ngram":"person","groupBy":"","groupByValue":"","count":"19"},{"ngram":"body","groupBy":"","groupByValue":"","count":"19"},{"ngram":"black","groupBy":"","groupByValue":"","count":"19"},{"ngram":"two","groupBy":"","groupByValue":"","count":"19"},{"ngram":"yes","groupBy":"","groupByValue":"","count":"19"},{"ngram":"lots","groupBy":"","groupByValue":"","count":"19"},{"ngram":"likes","groupBy":"","groupByValue":"","count":"19"},{"ngram":"discretion","groupBy":"","groupByValue":"","count":"19"},{"ngram":"meeting","groupBy":"","groupByValue":"","count":"19"},{"ngram":"care","groupBy":"","groupByValue":"","count":"19"},{"ngram":"true","groupBy":"","groupByValue":"","count":"19"},{"ngram":"r","groupBy":"","groupByValue":"","count":"19"},{"ngram":"soft","groupBy":"","groupByValue":"","count":"19"},{"ngram":"wanting","groupBy":"","groupByValue":"","count":"18"},{"ngram":"today","groupBy":"","groupByValue":"","count":"18"},{"ngram":"caring","groupBy":"","groupByValue":"","count":"18"},{"ngram":"chance","groupBy":"","groupByValue":"","count":"18"},{"ngram":"service","groupBy":"","groupByValue":"","count":"18"},{"ngram":"friendship","groupBy":"","groupByValue":"","count":"18"},{"ngram":"wine","groupBy":"","groupByValue":"","count":"18"},{"ngram":"taste","groupBy":"","groupByValue":"","count":"17"},{"ngram":"knows","groupBy":"","groupByValue":"","count":"17"},{"ngram":"tonight","groupBy":"","groupByValue":"","count":"17"},{"ngram":"side","groupBy":"","groupByValue":"","count":"17"},{"ngram":"safe","groupBy":"","groupByValue":"","count":"17"}]}