{"title":"Women NGram-3","total":"11327","sex":"Women","data":[{"ngram":"tall dark handsome","groupBy":"","groupByValue":"","count":"26"},{"ngram":"looking good time","groupBy":"","groupByValue":"","count":"25"},{"ngram":"just looking fun","groupBy":"","groupByValue":"","count":"20"},{"ngram":"guy looking fun","groupBy":"","groupByValue":"","count":"18"},{"ngram":"lets get together","groupBy":"","groupByValue":"","count":"17"},{"ngram":"looking discreet fun","groupBy":"","groupByValue":"","count":"14"},{"ngram":"live life fullest","groupBy":"","groupByValue":"","count":"12"},{"ngram":"looking little fun","groupBy":"","groupByValue":"","count":"12"},{"ngram":"looking fun times","groupBy":"","groupByValue":"","count":"10"},{"ngram":"fun fun fun","groupBy":"","groupByValue":"","count":"9"},{"ngram":"married man looking","groupBy":"","groupByValue":"","count":"9"},{"ngram":"nice guy looking","groupBy":"","groupByValue":"","count":"9"},{"ngram":"looking fun excitement","groupBy":"","groupByValue":"","count":"9"},{"ngram":"married male looking","groupBy":"","groupByValue":"","count":"8"},{"ngram":"meet new people","groupBy":"","groupByValue":"","count":"8"},{"ngram":"love wrong places","groupBy":"","groupByValue":"","count":"7"},{"ngram":"male looking fun","groupBy":"","groupByValue":"","count":"7"},{"ngram":"life short enjoy","groupBy":"","groupByValue":"","count":"7"},{"ngram":"looking love wrong","groupBy":"","groupByValue":"","count":"7"},{"ngram":"looking someone share","groupBy":"","groupByValue":"","count":"7"},{"ngram":"looking open minded","groupBy":"","groupByValue":"","count":"6"},{"ngram":"man looking fun","groupBy":"","groupByValue":"","count":"6"},{"ngram":"ventured nothing gained","groupBy":"","groupByValue":"","count":"6"},{"ngram":"open minded looking","groupBy":"","groupByValue":"","count":"6"},{"ngram":"lets fun together","groupBy":"","groupByValue":"","count":"6"},{"ngram":"love right places","groupBy":"","groupByValue":"","count":"6"},{"ngram":"looking meet interesting","groupBy":"","groupByValue":"","count":"6"},{"ngram":"attached male seeking","groupBy":"","groupByValue":"","count":"6"},{"ngram":"looking meet new","groupBy":"","groupByValue":"","count":"6"},{"ngram":"looking spice life","groupBy":"","groupByValue":"","count":"6"},{"ngram":"looking someone special","groupBy":"","groupByValue":"","count":"6"},{"ngram":"nothing ventured nothing","groupBy":"","groupByValue":"","count":"6"},{"ngram":"attractive male looking","groupBy":"","groupByValue":"","count":"6"},{"ngram":"looking love right","groupBy":"","groupByValue":"","count":"5"},{"ngram":"lean hard handsome","groupBy":"","groupByValue":"","count":"5"},{"ngram":"hi looking fun","groupBy":"","groupByValue":"","count":"5"},{"ngram":"hi ladies im","groupBy":"","groupByValue":"","count":"5"},{"ngram":"looking fun adventure","groupBy":"","groupByValue":"","count":"5"},{"ngram":"looking discreet relationship","groupBy":"","groupByValue":"","count":"5"},{"ngram":"looking forward meeting","groupBy":"","groupByValue":"","count":"5"},{"ngram":"looking strings attached","groupBy":"","groupByValue":"","count":"5"},{"ngram":"hot male looking","groupBy":"","groupByValue":"","count":"5"},{"ngram":"looking discreet encounters","groupBy":"","groupByValue":"","count":"5"},{"ngram":"hello ladies looking","groupBy":"","groupByValue":"","count":"5"},{"ngram":"looking great time","groupBy":"","groupByValue":"","count":"5"},{"ngram":"love give oral","groupBy":"","groupByValue":"","count":"5"},{"ngram":"ready willing able","groupBy":"","groupByValue":"","count":"5"},{"ngram":"dark lean hard","groupBy":"","groupByValue":"","count":"5"},{"ngram":"tall dark lean","groupBy":"","groupByValue":"","count":"5"},{"ngram":"let light fire","groupBy":"","groupByValue":"","count":"5"},{"ngram":"looking something new","groupBy":"","groupByValue":"","count":"5"},{"ngram":"attached male looking","groupBy":"","groupByValue":"","count":"5"},{"ngram":"just looking little","groupBy":"","groupByValue":"","count":"4"},{"ngram":"looking little spice","groupBy":"","groupByValue":"","count":"4"},{"ngram":"looking something special","groupBy":"","groupByValue":"","count":"4"},{"ngram":"looking someone fun","groupBy":"","groupByValue":"","count":"4"},{"ngram":"r u ready","groupBy":"","groupByValue":"","count":"4"},{"ngram":"add spice life","groupBy":"","groupByValue":"","count":"4"},{"ngram":"living life fullest","groupBy":"","groupByValue":"","count":"4"},{"ngram":"male seeking attached","groupBy":"","groupByValue":"","count":"4"},{"ngram":"like minded people","groupBy":"","groupByValue":"","count":"4"},{"ngram":"looking great fun","groupBy":"","groupByValue":"","count":"4"},{"ngram":"let show call","groupBy":"","groupByValue":"","count":"4"},{"ngram":"looking meet someone","groupBy":"","groupByValue":"","count":"4"},{"ngram":"ladies looking fun","groupBy":"","groupByValue":"","count":"4"},{"ngram":"show call tongue","groupBy":"","groupByValue":"","count":"4"},{"ngram":"little spice life","groupBy":"","groupByValue":"","count":"4"},{"ngram":"put smile face","groupBy":"","groupByValue":"","count":"4"},{"ngram":"just looking good","groupBy":"","groupByValue":"","count":"4"},{"ngram":"guy wants fun","groupBy":"","groupByValue":"","count":"4"},{"ngram":"one special lady","groupBy":"","groupByValue":"","count":"4"},{"ngram":"high sex drive","groupBy":"","groupByValue":"","count":"4"},{"ngram":"willing try anything","groupBy":"","groupByValue":"","count":"4"},{"ngram":"seeking attached female","groupBy":"","groupByValue":"","count":"4"},{"ngram":"variety spice life","groupBy":"","groupByValue":"","count":"4"},{"ngram":"dreams come true","groupBy":"","groupByValue":"","count":"4"},{"ngram":"seeking discreet fun","groupBy":"","groupByValue":"","count":"4"},{"ngram":"looking something extra","groupBy":"","groupByValue":"","count":"4"},{"ngram":"great sense humour","groupBy":"","groupByValue":"","count":"4"},{"ngram":"fun loving guy","groupBy":"","groupByValue":"","count":"4"},{"ngram":"looking discreet encounter","groupBy":"","groupByValue":"","count":"4"},{"ngram":"just lookin fun","groupBy":"","groupByValue":"","count":"4"},{"ngram":"easy going fun","groupBy":"","groupByValue":"","count":"4"},{"ngram":"looking friend lover","groupBy":"","groupByValue":"","count":"4"},{"ngram":"meet someone fun","groupBy":"","groupByValue":"","count":"4"},{"ngram":"enjoy life offer","groupBy":"","groupByValue":"","count":"3"},{"ngram":"can keep secret","groupBy":"","groupByValue":"","count":"3"},{"ngram":"lets get know","groupBy":"","groupByValue":"","count":"3"},{"ngram":"male looking discreet","groupBy":"","groupByValue":"","count":"3"},{"ngram":"life short let","groupBy":"","groupByValue":"","count":"3"},{"ngram":"looking fun good","groupBy":"","groupByValue":"","count":"3"},{"ngram":"fun guy looking","groupBy":"","groupByValue":"","count":"3"},{"ngram":"strings attached fun","groupBy":"","groupByValue":"","count":"3"},{"ngram":"looking casual fun","groupBy":"","groupByValue":"","count":"3"},{"ngram":"hi nice meet","groupBy":"","groupByValue":"","count":"3"},{"ngram":"lets get naked","groupBy":"","groupByValue":"","count":"3"},{"ngram":"single guy looking","groupBy":"","groupByValue":"","count":"3"},{"ngram":"looking 4 fun","groupBy":"","groupByValue":"","count":"3"},{"ngram":"lets see happens","groupBy":"","groupByValue":"","count":"3"},{"ngram":"hi im looking","groupBy":"","groupByValue":"","count":"3"},{"ngram":"white male seeking","groupBy":"","groupByValue":"","count":"3"},{"ngram":"looking strings fun","groupBy":"","groupByValue":"","count":"3"},{"ngram":"lets enjoy life","groupBy":"","groupByValue":"","count":"3"},{"ngram":"looking fun strings","groupBy":"","groupByValue":"","count":"3"},{"ngram":"looking add spice","groupBy":"","groupByValue":"","count":"3"},{"ngram":"sexy guy looking","groupBy":"","groupByValue":"","count":"3"},{"ngram":"cant get enough","groupBy":"","groupByValue":"","count":"3"},{"ngram":"looking fun loving","groupBy":"","groupByValue":"","count":"3"},{"ngram":"just nice guy","groupBy":"","groupByValue":"","count":"3"},{"ngram":"waiting 4 u","groupBy":"","groupByValue":"","count":"3"},{"ngram":"nice guy seeking","groupBy":"","groupByValue":"","count":"3"},{"ngram":"wanna come play","groupBy":"","groupByValue":"","count":"3"},{"ngram":"open minded male","groupBy":"","groupByValue":"","count":"3"},{"ngram":"good looking guy","groupBy":"","groupByValue":"","count":"3"},{"ngram":"hot oil massage","groupBy":"","groupByValue":"","count":"3"},{"ngram":"share good times","groupBy":"","groupByValue":"","count":"3"},{"ngram":"looking mature lady","groupBy":"","groupByValue":"","count":"3"},{"ngram":"thinking im thinking","groupBy":"","groupByValue":"","count":"3"},{"ngram":"female fun times","groupBy":"","groupByValue":"","count":"3"},{"ngram":"athletic male looking","groupBy":"","groupByValue":"","count":"3"},{"ngram":"just wanna fun","groupBy":"","groupByValue":"","count":"3"},{"ngram":"seeks mature women","groupBy":"","groupByValue":"","count":"3"},{"ngram":"life short live","groupBy":"","groupByValue":"","count":"3"},{"ngram":"just two us","groupBy":"","groupByValue":"","count":"3"},{"ngram":"looking fun right","groupBy":"","groupByValue":"","count":"3"},{"ngram":"always aim please","groupBy":"","groupByValue":"","count":"3"},{"ngram":"life short lets","groupBy":"","groupByValue":"","count":"3"},{"ngram":"hello looking fun","groupBy":"","groupByValue":"","count":"3"},{"ngram":"looking hot fun","groupBy":"","groupByValue":"","count":"3"},{"ngram":"looking someone can","groupBy":"","groupByValue":"","count":"3"},{"ngram":"im looking fun","groupBy":"","groupByValue":"","count":"3"},{"ngram":"hi ladies lets","groupBy":"","groupByValue":"","count":"3"},{"ngram":"male looking adventure","groupBy":"","groupByValue":"","count":"3"},{"ngram":"gentleman looking lady","groupBy":"","groupByValue":"","count":"3"},{"ngram":"love play fun","groupBy":"","groupByValue":"","count":"3"},{"ngram":"young guy looking","groupBy":"","groupByValue":"","count":"3"},{"ngram":"looking older woman","groupBy":"","groupByValue":"","count":"3"},{"ngram":"yr old male","groupBy":"","groupByValue":"","count":"3"},{"ngram":"handsome man looking","groupBy":"","groupByValue":"","count":"3"},{"ngram":"hot hot hot","groupBy":"","groupByValue":"","count":"3"},{"ngram":"looking attached female","groupBy":"","groupByValue":"","count":"3"},{"ngram":"young professional seeking","groupBy":"","groupByValue":"","count":"3"},{"ngram":"going fun loving","groupBy":"","groupByValue":"","count":"3"},{"ngram":"male looking little","groupBy":"","groupByValue":"","count":"3"},{"ngram":"looking something different","groupBy":"","groupByValue":"","count":"3"},{"ngram":"looking good times","groupBy":"","groupByValue":"","count":"3"},{"ngram":"seeking fun times","groupBy":"","groupByValue":"","count":"3"},{"ngram":"fun right places","groupBy":"","groupByValue":"","count":"3"},{"ngram":"looking daytime fun","groupBy":"","groupByValue":"","count":"3"},{"ngram":"fantasy come true","groupBy":"","groupByValue":"","count":"3"},{"ngram":"stop take look","groupBy":"","groupByValue":"","count":"2"},{"ngram":"looking someone like","groupBy":"","groupByValue":"","count":"2"},{"ngram":"man looking discrete","groupBy":"","groupByValue":"","count":"2"},{"ngram":"just checking things","groupBy":"","groupByValue":"","count":"2"},{"ngram":"look lovely tonight","groupBy":"","groupByValue":"","count":"2"},{"ngram":"ill try anything","groupBy":"","groupByValue":"","count":"2"},{"ngram":"like meet nice","groupBy":"","groupByValue":"","count":"2"},{"ngram":"married male seeking","groupBy":"","groupByValue":"","count":"2"},{"ngram":"music especially jazz","groupBy":"","groupByValue":"","count":"2"},{"ngram":"can keep secretcan","groupBy":"","groupByValue":"","count":"2"},{"ngram":"young gun looking","groupBy":"","groupByValue":"","count":"2"},{"ngram":"looking intelligent elegant","groupBy":"","groupByValue":"","count":"2"},{"ngram":"sensuality high adventure","groupBy":"","groupByValue":"","count":"2"},{"ngram":"looking lover wont","groupBy":"","groupByValue":"","count":"2"},{"ngram":"looking special friend","groupBy":"","groupByValue":"","count":"2"},{"ngram":"looking find something","groupBy":"","groupByValue":"","count":"2"},{"ngram":"know till try","groupBy":"","groupByValue":"","count":"2"},{"ngram":"open minded women","groupBy":"","groupByValue":"","count":"2"},{"ngram":"want get fun","groupBy":"","groupByValue":"","count":"2"},{"ngram":"looking mature women","groupBy":"","groupByValue":"","count":"2"},{"ngram":"easy going male","groupBy":"","groupByValue":"","count":"2"},{"ngram":"attached looking fun","groupBy":"","groupByValue":"","count":"2"},{"ngram":"ill never tell","groupBy":"","groupByValue":"","count":"2"},{"ngram":"36 year old","groupBy":"","groupByValue":"","count":"2"},{"ngram":"hot young stud","groupBy":"","groupByValue":"","count":"2"},{"ngram":"man seeks attached","groupBy":"","groupByValue":"","count":"2"},{"ngram":"hi pleasure meet","groupBy":"","groupByValue":"","count":"2"},{"ngram":"looking married females","groupBy":"","groupByValue":"","count":"2"},{"ngram":"love music especially","groupBy":"","groupByValue":"","count":"2"},{"ngram":"open minded fun","groupBy":"","groupByValue":"","count":"2"},{"ngram":"younger guy looking","groupBy":"","groupByValue":"","count":"2"},{"ngram":"discreet fun time","groupBy":"","groupByValue":"","count":"2"},{"ngram":"easy going looking","groupBy":"","groupByValue":"","count":"2"},{"ngram":"looking little adventure","groupBy":"","groupByValue":"","count":"2"},{"ngram":"male seeking females","groupBy":"","groupByValue":"","count":"2"},{"ngram":"shall leave breathless","groupBy":"","groupByValue":"","count":"2"},{"ngram":"little fun side","groupBy":"","groupByValue":"","count":"2"},{"ngram":"something new exciting","groupBy":"","groupByValue":"","count":"2"},{"ngram":"male looking older","groupBy":"","groupByValue":"","count":"2"},{"ngram":"roses red violets","groupBy":"","groupByValue":"","count":"2"},{"ngram":"looking something discreet","groupBy":"","groupByValue":"","count":"2"},{"ngram":"please women orally","groupBy":"","groupByValue":"","count":"2"},{"ngram":"mid 30s male","groupBy":"","groupByValue":"","count":"2"},{"ngram":"kind heart excitable","groupBy":"","groupByValue":"","count":"2"},{"ngram":"hair blue eyed","groupBy":"","groupByValue":"","count":"2"},{"ngram":"male looking good","groupBy":"","groupByValue":"","count":"2"},{"ngram":"fun loving girl","groupBy":"","groupByValue":"","count":"2"},{"ngram":"looking new adventure","groupBy":"","groupByValue":"","count":"2"},{"ngram":"looking hot sex","groupBy":"","groupByValue":"","count":"2"},{"ngram":"im looking someone","groupBy":"","groupByValue":"","count":"2"},{"ngram":"let make feel","groupBy":"","groupByValue":"","count":"2"},{"ngram":"enjoy much can","groupBy":"","groupByValue":"","count":"2"},{"ngram":"looking miss right","groupBy":"","groupByValue":"","count":"2"},{"ngram":"trying new things","groupBy":"","groupByValue":"","count":"2"},{"ngram":"looking meet one","groupBy":"","groupByValue":"","count":"2"},{"ngram":"white married male","groupBy":"","groupByValue":"","count":"2"},{"ngram":"looking fun like","groupBy":"","groupByValue":"","count":"2"},{"ngram":"guy looking discreet","groupBy":"","groupByValue":"","count":"2"},{"ngram":"male looking meet","groupBy":"","groupByValue":"","count":"2"},{"ngram":"minded people experience","groupBy":"","groupByValue":"","count":"2"},{"ngram":"stop looking im","groupBy":"","groupByValue":"","count":"2"},{"ngram":"just looking something","groupBy":"","groupByValue":"","count":"2"},{"ngram":"goood clean fun","groupBy":"","groupByValue":"","count":"2"},{"ngram":"looking fun wrong","groupBy":"","groupByValue":"","count":"2"},{"ngram":"add little spice","groupBy":"","groupByValue":"","count":"2"},{"ngram":"want rock world","groupBy":"","groupByValue":"","count":"2"},{"ngram":"lady fisrt time","groupBy":"","groupByValue":"","count":"2"},{"ngram":"long term relationship","groupBy":"","groupByValue":"","count":"2"},{"ngram":"im looking woman","groupBy":"","groupByValue":"","count":"2"},{"ngram":"strings just fun","groupBy":"","groupByValue":"","count":"2"},{"ngram":"seeking attached females","groupBy":"","groupByValue":"","count":"2"},{"ngram":"looking fun woman","groupBy":"","groupByValue":"","count":"2"},{"ngram":"always finish last","groupBy":"","groupByValue":"","count":"2"},{"ngram":"hi ladies looking","groupBy":"","groupByValue":"","count":"2"},{"ngram":"seeks older women","groupBy":"","groupByValue":"","count":"2"},{"ngram":"happiness state mind","groupBy":"","groupByValue":"","count":"2"},{"ngram":"looking lust excitement","groupBy":"","groupByValue":"","count":"2"},{"ngram":"ladies lokking something","groupBy":"","groupByValue":"","count":"2"},{"ngram":"hard play harder","groupBy":"","groupByValue":"","count":"2"},{"ngram":"meet like minded","groupBy":"","groupByValue":"","count":"2"},{"ngram":"just looking around","groupBy":"","groupByValue":"","count":"2"},{"ngram":"think can handle","groupBy":"","groupByValue":"","count":"2"},{"ngram":"looking special someone","groupBy":"","groupByValue":"","count":"2"},{"ngram":"lets chat see","groupBy":"","groupByValue":"","count":"2"},{"ngram":"watch quiet ones","groupBy":"","groupByValue":"","count":"2"},{"ngram":"need little spice","groupBy":"","groupByValue":"","count":"2"},{"ngram":"good time long","groupBy":"","groupByValue":"","count":"2"},{"ngram":"lets just get","groupBy":"","groupByValue":"","count":"2"},{"ngram":"pour vous madame","groupBy":"","groupByValue":"","count":"2"},{"ngram":"discreet kinky fun","groupBy":"","groupByValue":"","count":"2"},{"ngram":"trying something new","groupBy":"","groupByValue":"","count":"2"},{"ngram":"little erotic playime","groupBy":"","groupByValue":"","count":"2"},{"ngram":"best yet come","groupBy":"","groupByValue":"","count":"2"},{"ngram":"looking fun excitment","groupBy":"","groupByValue":"","count":"2"},{"ngram":"see takes us","groupBy":"","groupByValue":"","count":"2"},{"ngram":"hi just looking","groupBy":"","groupByValue":"","count":"2"},{"ngram":"looking meet fun","groupBy":"","groupByValue":"","count":"2"},{"ngram":"lets make happen","groupBy":"","groupByValue":"","count":"2"},{"ngram":"lets try something","groupBy":"","groupByValue":"","count":"2"},{"ngram":"looking good company","groupBy":"","groupByValue":"","count":"2"}]}